bpdp/__init__.py
bpdp/_bpdp.py
bpdp/filter.py
bpdp/resample/__init__.py
bpdp/resample/akima.py
bpdp/resample/fseries.py
bpdp/resample/makima.py
bpdp/window/__init__.py
bpdp/window/hann.py
bpdp/window/k6.py
bpdp-0.1.0.dist-info/METADATA
bpdp-0.1.0.dist-info/WHEEL
bpdp-0.1.0.dist-info/licenses/LICENSE.txt
bpdp-0.1.0.dist-info/RECORD
