Metadata-Version: 2.4
Name: bpdp
Version: 0.1.0
Summary: Epoch extraction with bandpass filter and dynamic progamming
Author-email: "林彥廷(Yen-Ting, Lin)" <d26923050@gmail.com>
License-Expression: BSD-3-Clause
License-File: LICENSE.txt
Classifier: Programming Language :: Python :: 3
Classifier: Topic :: Multimedia :: Sound/Audio :: Analysis
Classifier: Topic :: Multimedia :: Sound/Audio :: Speech
Requires-Python: >=3.10
Requires-Dist: torch>=2.0.0
